bubuxiong_word_count/__init__.py
bubuxiong_word_count/cmdline.py
bubuxiong_word_count/counter.py
bubuxiong_word_count-0.1.0.dist-info/LICENSE
bubuxiong_word_count-0.1.0.dist-info/METADATA
bubuxiong_word_count-0.1.0.dist-info/WHEEL
bubuxiong_word_count-0.1.0.dist-info/entry_points.txt
bubuxiong_word_count-0.1.0.dist-info/RECORD
