Metadata-Version: 2.1
Name: bubuxiong_word_count
Version: 0.1.0
Summary: Word Count Project.
License: MIT
Author: test
Author-email: test@example.com
Requires-Python: >=3.10,<4.0
Classifier: License :: OSI Approved :: MIT License
Classifier: Operating System :: OS Independent
Classifier: Programming Language :: Python :: 3
Classifier: Programming Language :: Python :: 3.10
Classifier: Programming Language :: Python :: 3.11
